rlda
