Metadata-Version: 1.0
Name: rlda
Version: 0.9
Summary: A module to use robust lda topics for the study of text
Home-page: http://github.com/CasAndreu/rlda
Author: Andreu Casas
Author-email: acasas2@uw.edu
License: MIT
Platform: UNKNOWN
